<?xml version='1.0' encoding='utf-8'?>
<rdf:RDF xmlns:rdf="http://www.w3.org/1999/02/22-rdf-syntax-ns#"><Alignment><xml>1</xml><level>0</level><type>??</type><map><Cell><entity1 rdf:resource="&lt;http://dbkwik.webdatacommons.org/memory-alpha.wikia.com/resource/0413_theta&gt;" /><entity2 rdf:resource="&lt;http://dbkwik.webdatacommons.org/memory-beta.wikia.com/resource/1020_octantis&gt;" /><relation>=</relation><measure rdf:datatype="xsd:float">1.0</measure></Cell></map><map><Cell><entity1 rdf:resource="&lt;http://dbkwik.webdatacommons.org/memory-alpha.wikia.com/resource/0413_theta&gt;" /><entity2 rdf:resource="&lt;http://dbkwik.webdatacommons.org/memory-beta.wikia.com/resource/...sacrifice_of_angels&gt;" /><relation>=</relation><measure rdf:datatype="xsd:float">1.0</measure></Cell></map><map><Cell><entity1 rdf:resource="&lt;http://dbkwik.webdatacommons.org/memory-alpha.wikia.com/resource/0413_theta&gt;" /><entity2 rdf:resource="&lt;http://dbkwik.webdatacommons.org/memory-beta.wikia.com/resource/127_scorpii&gt;" /><relation>=</relation><measure rdf:datatype="xsd:float">1.0</measure></Cell></map><map><Cell><entity1 rdf:resource="&lt;http://dbkwik.webdatacommons.org/memory-alpha.wikia.com/resource/0413_theta&gt;" /><entity2 rdf:resource="&lt;http://dbkwik.webdatacommons.org/memory-beta.wikia.com/resource/15th_squad&gt;" /><relation>=</relation><measure rdf:datatype="xsd:float">1.0</measure></Cell></map><map><Cell><entity1 rdf:resource="&lt;http://dbkwik.webdatacommons.org/memory-alpha.wikia.com/resource/0413_theta&gt;" /><entity2 rdf:resource="&lt;http://dbkwik.webdatacommons.org/memory-beta.wikia.com/resource/1800s&gt;" /><relation>=</relation><measure rdf:datatype="xsd:float">1.0</measure></Cell></map><map><Cell><entity1 rdf:resource="&lt;http://dbkwik.webdatacommons.org/memory-alpha.wikia.com/resource/0413_theta&gt;" /><entity2 rdf:resource="&lt;http://dbkwik.webdatacommons.org/memory-beta.wikia.com/resource/1810s&gt;" /><relation>=</relation><measure rdf:datatype="xsd:float">1.0</measure></Cell></map><map><Cell><entity1 rdf:resource="&lt;http://dbkwik.webdatacommons.org/memory-alpha.wikia.com/resource/0413_theta&gt;" /><entity2 rdf:resource="&lt;http://dbkwik.webdatacommons.org/memory-beta.wikia.com/resource/1840s&gt;" /><relation>=</relation><measure rdf:datatype="xsd:float">1.0</measure></Cell></map><map><Cell><entity1 rdf:resource="&lt;http://dbkwik.webdatacommons.org/memory-alpha.wikia.com/resource/0413_theta&gt;" /><entity2 rdf:resource="&lt;http://dbkwik.webdatacommons.org/memory-beta.wikia.com/resource/1865_serpens&gt;" /><relation>=</relation><measure rdf:datatype="xsd:float">1.0</measure></Cell></map><map><Cell><entity1 rdf:resource="&lt;http://dbkwik.webdatacommons.org/memory-alpha.wikia.com/resource/0413_theta&gt;" /><entity2 rdf:resource="&lt;http://dbkwik.webdatacommons.org/memory-beta.wikia.com/resource/1870s&gt;" /><relation>=</relation><measure rdf:datatype="xsd:float">1.0</measure></Cell></map><map><Cell><entity1 rdf:resource="&lt;http://dbkwik.webdatacommons.org/memory-alpha.wikia.com/resource/0413_theta&gt;" /><entity2 rdf:resource="&lt;http://dbkwik.webdatacommons.org/memory-beta.wikia.com/resource/1880s&gt;" /><relation>=</relation><measure rdf:datatype="xsd:float">1.0</measure></Cell></map><map><Cell><entity1 rdf:resource="&lt;http://dbkwik.webdatacommons.org/memory-alpha.wikia.com/resource/0413_theta&gt;" /><entity2 rdf:resource="&lt;http://dbkwik.webdatacommons.org/memory-beta.wikia.com/resource/1_centauri&gt;" /><relation>=</relation><measure rdf:datatype="xsd:float">1.0</measure></Cell></map><map><Cell><entity1 rdf:resource="&lt;http://dbkwik.webdatacommons.org/memory-alpha.wikia.com/resource/0413_theta&gt;" /><entity2 rdf:resource="&lt;http://dbkwik.webdatacommons.org/memory-beta.wikia.com/resource/2265_starfleet_personnel_deaths&gt;" /><relation>=</relation><measure rdf:datatype="xsd:float">1.0</measure></Cell></map><map><Cell><entity1 rdf:resource="&lt;http://dbkwik.webdatacommons.org/memory-alpha.wikia.com/resource/0413_theta&gt;" /><entity2 rdf:resource="&lt;http://dbkwik.webdatacommons.org/memory-beta.wikia.com/resource/2266_starfleet_personnel_deaths&gt;" /><relation>=</relation><measure rdf:datatype="xsd:float">1.0</measure></Cell></map><map><Cell><entity1 rdf:resource="&lt;http://dbkwik.webdatacommons.org/memory-alpha.wikia.com/resource/0413_theta&gt;" /><entity2 rdf:resource="&lt;http://dbkwik.webdatacommons.org/memory-beta.wikia.com/resource/2267_starfleet_personnel_deaths&gt;" /><relation>=</relation><measure rdf:datatype="xsd:float">1.0</measure></Cell></map><map><Cell><entity1 rdf:resource="&lt;http://dbkwik.webdatacommons.org/memory-alpha.wikia.com/resource/0413_theta&gt;" /><entity2 rdf:resource="&lt;http://dbkwik.webdatacommons.org/memory-beta.wikia.com/resource/2270_starfleet_personnel_deaths&gt;" /><relation>=</relation><measure rdf:datatype="xsd:float">1.0</measure></Cell></map><map><Cell><entity1 rdf:resource="&lt;http://dbkwik.webdatacommons.org/memory-alpha.wikia.com/resource/0413_theta&gt;" /><entity2 rdf:resource="&lt;http://dbkwik.webdatacommons.org/memory-beta.wikia.com/resource/2271_starfleet_personnel_deaths&gt;" /><relation>=</relation><measure rdf:datatype="xsd:float">1.0</measure></Cell></map><map><Cell><entity1 rdf:resource="&lt;http://dbkwik.webdatacommons.org/memory-alpha.wikia.com/resource/0413_theta&gt;" /><entity2 rdf:resource="&lt;http://dbkwik.webdatacommons.org/memory-beta.wikia.com/resource/2367_starfleet_personnel_deaths&gt;" /><relation>=</relation><measure rdf:datatype="xsd:float">1.0</measure></Cell></map><map><Cell><entity1 rdf:resource="&lt;http://dbkwik.webdatacommons.org/memory-alpha.wikia.com/resource/0413_theta&gt;" /><entity2 rdf:resource="&lt;http://dbkwik.webdatacommons.org/memory-beta.wikia.com/resource/2373_starfleet_personnel_deaths&gt;" /><relation>=</relation><measure rdf:datatype="xsd:float">1.0</measure></Cell></map><map><Cell><entity1 rdf:resource="&lt;http://dbkwik.webdatacommons.org/memory-alpha.wikia.com/resource/10_april&gt;" /><entity2 rdf:resource="&lt;http://dbkwik.webdatacommons.org/memory-beta.wikia.com/resource/'q'uandary&gt;" /><relation>=</relation><measure rdf:datatype="xsd:float">1.0</measure></Cell></map><map><Cell><entity1 rdf:resource="&lt;http://dbkwik.webdatacommons.org/memory-alpha.wikia.com/resource/10_april&gt;" /><entity2 rdf:resource="&lt;http://dbkwik.webdatacommons.org/memory-beta.wikia.com/resource/11_lacerti&gt;" /><relation>=</relation><measure rdf:datatype="xsd:float">1.0</measure></Cell></map><map><Cell><entity1 rdf:resource="&lt;http://dbkwik.webdatacommons.org/memory-alpha.wikia.com/resource/10_april&gt;" /><entity2 rdf:resource="&lt;http://dbkwik.webdatacommons.org/memory-beta.wikia.com/resource/1616_ophiuchi_vi&gt;" /><relation>=</relation><measure rdf:datatype="xsd:float">1.0</measure></Cell></map><map><Cell><entity1 rdf:resource="&lt;http://dbkwik.webdatacommons.org/memory-alpha.wikia.com/resource/10_april&gt;" /><entity2 rdf:resource="&lt;http://dbkwik.webdatacommons.org/memory-beta.wikia.com/resource/1810s&gt;" /><relation>=</relation><measure rdf:datatype="xsd:float">1.0</measure></Cell></map><map><Cell><entity1 rdf:resource="&lt;http://dbkwik.webdatacommons.org/memory-alpha.wikia.com/resource/10_april&gt;" /><entity2 rdf:resource="&lt;http://dbkwik.webdatacommons.org/memory-beta.wikia.com/resource/1890s&gt;" /><relation>=</relation><measure rdf:datatype="xsd:float">1.0</measure></Cell></map><map><Cell><entity1 rdf:resource="&lt;http://dbkwik.webdatacommons.org/memory-alpha.wikia.com/resource/10_april&gt;" /><entity2 rdf:resource="&lt;http://dbkwik.webdatacommons.org/memory-beta.wikia.com/resource/2000-2049_sfc&gt;" /><relation>=</relation><measure rdf:datatype="xsd:float">1.0</measure></Cell></map><map><Cell><entity1 rdf:resource="&lt;http://dbkwik.webdatacommons.org/memory-alpha.wikia.com/resource/10_april&gt;" /><entity2 rdf:resource="&lt;http://dbkwik.webdatacommons.org/memory-beta.wikia.com/resource/2371_cardassian_coup&gt;" /><relation>=</relation><measure rdf:datatype="xsd:float">1.0</measure></Cell></map><map><Cell><entity1 rdf:resource="&lt;http://dbkwik.webdatacommons.org/memory-alpha.wikia.com/resource/10_april&gt;" /><entity2 rdf:resource="&lt;http://dbkwik.webdatacommons.org/memory-beta.wikia.com/resource/2371_starfleet_personnel_deaths&gt;" /><relation>=</relation><measure rdf:datatype="xsd:float">1.0</measure></Cell></map><map><Cell><entity1 rdf:resource="&lt;http://dbkwik.webdatacommons.org/memory-alpha.wikia.com/resource/(a_little_adventure...)_..._goes_a_long_way!_the_conclusion!&gt;" /><entity2 rdf:resource="&lt;http://dbkwik.webdatacommons.org/memory-beta.wikia.com/resource/'q'uandary&gt;" /><relation>=</relation><measure rdf:datatype="xsd:float">1.0</measure></Cell></map><map><Cell><entity1 rdf:resource="&lt;http://dbkwik.webdatacommons.org/memory-alpha.wikia.com/resource/(a_little_adventure...)_..._goes_a_long_way!_the_conclusion!&gt;" /><entity2 rdf:resource="&lt;http://dbkwik.webdatacommons.org/memory-beta.wikia.com/resource/11_lacerti&gt;" /><relation>=</relation><measure rdf:datatype="xsd:float">1.0</measure></Cell></map><map><Cell><entity1 rdf:resource="&lt;http://dbkwik.webdatacommons.org/memory-alpha.wikia.com/resource/(a_little_adventure...)_..._goes_a_long_way!_the_conclusion!&gt;" /><entity2 rdf:resource="&lt;http://dbkwik.webdatacommons.org/memory-beta.wikia.com/resource/1616_ophiuchi_vi&gt;" /><relation>=</relation><measure rdf:datatype="xsd:float">1.0</measure></Cell></map><map><Cell><entity1 rdf:resource="&lt;http://dbkwik.webdatacommons.org/memory-alpha.wikia.com/resource/(a_little_adventure...)_..._goes_a_long_way!_the_conclusion!&gt;" /><entity2 rdf:resource="&lt;http://dbkwik.webdatacommons.org/memory-beta.wikia.com/resource/1810s&gt;" /><relation>=</relation><measure rdf:datatype="xsd:float">1.0</measure></Cell></map><map><Cell><entity1 rdf:resource="&lt;http://dbkwik.webdatacommons.org/memory-alpha.wikia.com/resource/(a_little_adventure...)_..._goes_a_long_way!_the_conclusion!&gt;" /><entity2 rdf:resource="&lt;http://dbkwik.webdatacommons.org/memory-beta.wikia.com/resource/1890s&gt;" /><relation>=</relation><measure rdf:datatype="xsd:float">1.0</measure></Cell></map><map><Cell><entity1 rdf:resource="&lt;http://dbkwik.webdatacommons.org/memory-alpha.wikia.com/resource/(a_little_adventure...)_..._goes_a_long_way!_the_conclusion!&gt;" /><entity2 rdf:resource="&lt;http://dbkwik.webdatacommons.org/memory-beta.wikia.com/resource/2000-2049_sfc&gt;" /><relation>=</relation><measure rdf:datatype="xsd:float">1.0</measure></Cell></map><map><Cell><entity1 rdf:resource="&lt;http://dbkwik.webdatacommons.org/memory-alpha.wikia.com/resource/(a_little_adventure...)_..._goes_a_long_way!_the_conclusion!&gt;" /><entity2 rdf:resource="&lt;http://dbkwik.webdatacommons.org/memory-beta.wikia.com/resource/2371_cardassian_coup&gt;" /><relation>=</relation><measure rdf:datatype="xsd:float">1.0</measure></Cell></map><map><Cell><entity1 rdf:resource="&lt;http://dbkwik.webdatacommons.org/memory-alpha.wikia.com/resource/(a_little_adventure...)_..._goes_a_long_way!_the_conclusion!&gt;" /><entity2 rdf:resource="&lt;http://dbkwik.webdatacommons.org/memory-beta.wikia.com/resource/2371_starfleet_personnel_deaths&gt;" /><relation>=</relation><measure rdf:datatype="xsd:float">1.0</measure></Cell></map><map><Cell><entity1 rdf:resource="&lt;http://dbkwik.webdatacommons.org/memory-alpha.wikia.com/resource/.38_police_special&gt;" /><entity2 rdf:resource="&lt;http://dbkwik.webdatacommons.org/memory-beta.wikia.com/resource/'q'uandary&gt;" /><relation>=</relation><measure rdf:datatype="xsd:float">1.0</measure></Cell></map><map><Cell><entity1 rdf:resource="&lt;http://dbkwik.webdatacommons.org/memory-alpha.wikia.com/resource/.38_police_special&gt;" /><entity2 rdf:resource="&lt;http://dbkwik.webdatacommons.org/memory-beta.wikia.com/resource/11_lacerti&gt;" /><relation>=</relation><measure rdf:datatype="xsd:float">1.0</measure></Cell></map><map><Cell><entity1 rdf:resource="&lt;http://dbkwik.webdatacommons.org/memory-alpha.wikia.com/resource/.38_police_special&gt;" /><entity2 rdf:resource="&lt;http://dbkwik.webdatacommons.org/memory-beta.wikia.com/resource/1616_ophiuchi_vi&gt;" /><relation>=</relation><measure rdf:datatype="xsd:float">1.0</measure></Cell></map><map><Cell><entity1 rdf:resource="&lt;http://dbkwik.webdatacommons.org/memory-alpha.wikia.com/resource/.38_police_special&gt;" /><entity2 rdf:resource="&lt;http://dbkwik.webdatacommons.org/memory-beta.wikia.com/resource/1810s&gt;" /><relation>=</relation><measure rdf:datatype="xsd:float">1.0</measure></Cell></map><map><Cell><entity1 rdf:resource="&lt;http://dbkwik.webdatacommons.org/memory-alpha.wikia.com/resource/.38_police_special&gt;" /><entity2 rdf:resource="&lt;http://dbkwik.webdatacommons.org/memory-beta.wikia.com/resource/1890s&gt;" /><relation>=</relation><measure rdf:datatype="xsd:float">1.0</measure></Cell></map><map><Cell><entity1 rdf:resource="&lt;http://dbkwik.webdatacommons.org/memory-alpha.wikia.com/resource/.38_police_special&gt;" /><entity2 rdf:resource="&lt;http://dbkwik.webdatacommons.org/memory-beta.wikia.com/resource/2000-2049_sfc&gt;" /><relation>=</relation><measure rdf:datatype="xsd:float">1.0</measure></Cell></map><map><Cell><entity1 rdf:resource="&lt;http://dbkwik.webdatacommons.org/memory-alpha.wikia.com/resource/.38_police_special&gt;" /><entity2 rdf:resource="&lt;http://dbkwik.webdatacommons.org/memory-beta.wikia.com/resource/2371_cardassian_coup&gt;" /><relation>=</relation><measure rdf:datatype="xsd:float">1.0</measure></Cell></map><map><Cell><entity1 rdf:resource="&lt;http://dbkwik.webdatacommons.org/memory-alpha.wikia.com/resource/.38_police_special&gt;" /><entity2 rdf:resource="&lt;http://dbkwik.webdatacommons.org/memory-beta.wikia.com/resource/2371_starfleet_personnel_deaths&gt;" /><relation>=</relation><measure rdf:datatype="xsd:float">1.0</measure></Cell></map><map><Cell><entity1 rdf:resource="&lt;http://dbkwik.webdatacommons.org/memory-alpha.wikia.com/resource/10_august&gt;" /><entity2 rdf:resource="&lt;http://dbkwik.webdatacommons.org/memory-beta.wikia.com/resource/'q'uandary&gt;" /><relation>=</relation><measure rdf:datatype="xsd:float">1.0</measure></Cell></map><map><Cell><entity1 rdf:resource="&lt;http://dbkwik.webdatacommons.org/memory-alpha.wikia.com/resource/10_august&gt;" /><entity2 rdf:resource="&lt;http://dbkwik.webdatacommons.org/memory-beta.wikia.com/resource/11_lacerti&gt;" /><relation>=</relation><measure rdf:datatype="xsd:float">1.0</measure></Cell></map><map><Cell><entity1 rdf:resource="&lt;http://dbkwik.webdatacommons.org/memory-alpha.wikia.com/resource/10_august&gt;" /><entity2 rdf:resource="&lt;http://dbkwik.webdatacommons.org/memory-beta.wikia.com/resource/1616_ophiuchi_vi&gt;" /><relation>=</relation><measure rdf:datatype="xsd:float">1.0</measure></Cell></map><map><Cell><entity1 rdf:resource="&lt;http://dbkwik.webdatacommons.org/memory-alpha.wikia.com/resource/10_august&gt;" /><entity2 rdf:resource="&lt;http://dbkwik.webdatacommons.org/memory-beta.wikia.com/resource/1810s&gt;" /><relation>=</relation><measure rdf:datatype="xsd:float">1.0</measure></Cell></map><map><Cell><entity1 rdf:resource="&lt;http://dbkwik.webdatacommons.org/memory-alpha.wikia.com/resource/10_august&gt;" /><entity2 rdf:resource="&lt;http://dbkwik.webdatacommons.org/memory-beta.wikia.com/resource/1890s&gt;" /><relation>=</relation><measure rdf:datatype="xsd:float">1.0</measure></Cell></map><map><Cell><entity1 rdf:resource="&lt;http://dbkwik.webdatacommons.org/memory-alpha.wikia.com/resource/10_august&gt;" /><entity2 rdf:resource="&lt;http://dbkwik.webdatacommons.org/memory-beta.wikia.com/resource/2000-2049_sfc&gt;" /><relation>=</relation><measure rdf:datatype="xsd:float">1.0</measure></Cell></map><map><Cell><entity1 rdf:resource="&lt;http://dbkwik.webdatacommons.org/memory-alpha.wikia.com/resource/10_august&gt;" /><entity2 rdf:resource="&lt;http://dbkwik.webdatacommons.org/memory-beta.wikia.com/resource/2371_cardassian_coup&gt;" /><relation>=</relation><measure rdf:datatype="xsd:float">1.0</measure></Cell></map><map><Cell><entity1 rdf:resource="&lt;http://dbkwik.webdatacommons.org/memory-alpha.wikia.com/resource/10_august&gt;" /><entity2 rdf:resource="&lt;http://dbkwik.webdatacommons.org/memory-beta.wikia.com/resource/2371_starfleet_personnel_deaths&gt;" /><relation>=</relation><measure rdf:datatype="xsd:float">1.0</measure></Cell></map><map><Cell><entity1 rdf:resource="&lt;http://dbkwik.webdatacommons.org/memory-alpha.wikia.com/resource/1001:_first_odyssey&gt;" /><entity2 rdf:resource="&lt;http://dbkwik.webdatacommons.org/memory-beta.wikia.com/resource/1020_octantis&gt;" /><relation>=</relation><measure rdf:datatype="xsd:float">1.0</measure></Cell></map><map><Cell><entity1 rdf:resource="&lt;http://dbkwik.webdatacommons.org/memory-alpha.wikia.com/resource/1001:_first_odyssey&gt;" /><entity2 rdf:resource="&lt;http://dbkwik.webdatacommons.org/memory-beta.wikia.com/resource/...sacrifice_of_angels&gt;" /><relation>=</relation><measure rdf:datatype="xsd:float">1.0</measure></Cell></map><map><Cell><entity1 rdf:resource="&lt;http://dbkwik.webdatacommons.org/memory-alpha.wikia.com/resource/1001:_first_odyssey&gt;" /><entity2 rdf:resource="&lt;http://dbkwik.webdatacommons.org/memory-beta.wikia.com/resource/127_scorpii&gt;" /><relation>=</relation><measure rdf:datatype="xsd:float">1.0</measure></Cell></map><map><Cell><entity1 rdf:resource="&lt;http://dbkwik.webdatacommons.org/memory-alpha.wikia.com/resource/1001:_first_odyssey&gt;" /><entity2 rdf:resource="&lt;http://dbkwik.webdatacommons.org/memory-beta.wikia.com/resource/15th_squad&gt;" /><relation>=</relation><measure rdf:datatype="xsd:float">1.0</measure></Cell></map><map><Cell><entity1 rdf:resource="&lt;http://dbkwik.webdatacommons.org/memory-alpha.wikia.com/resource/1001:_first_odyssey&gt;" /><entity2 rdf:resource="&lt;http://dbkwik.webdatacommons.org/memory-beta.wikia.com/resource/1800s&gt;" /><relation>=</relation><measure rdf:datatype="xsd:float">1.0</measure></Cell></map><map><Cell><entity1 rdf:resource="&lt;http://dbkwik.webdatacommons.org/memory-alpha.wikia.com/resource/1001:_first_odyssey&gt;" /><entity2 rdf:resource="&lt;http://dbkwik.webdatacommons.org/memory-beta.wikia.com/resource/1810s&gt;" /><relation>=</relation><measure rdf:datatype="xsd:float">1.0</measure></Cell></map><map><Cell><entity1 rdf:resource="&lt;http://dbkwik.webdatacommons.org/memory-alpha.wikia.com/resource/1001:_first_odyssey&gt;" /><entity2 rdf:resource="&lt;http://dbkwik.webdatacommons.org/memory-beta.wikia.com/resource/1840s&gt;" /><relation>=</relation><measure rdf:datatype="xsd:float">1.0</measure></Cell></map><map><Cell><entity1 rdf:resource="&lt;http://dbkwik.webdatacommons.org/memory-alpha.wikia.com/resource/1001:_first_odyssey&gt;" /><entity2 rdf:resource="&lt;http://dbkwik.webdatacommons.org/memory-beta.wikia.com/resource/1865_serpens&gt;" /><relation>=</relation><measure rdf:datatype="xsd:float">1.0</measure></Cell></map><map><Cell><entity1 rdf:resource="&lt;http://dbkwik.webdatacommons.org/memory-alpha.wikia.com/resource/1001:_first_odyssey&gt;" /><entity2 rdf:resource="&lt;http://dbkwik.webdatacommons.org/memory-beta.wikia.com/resource/1870s&gt;" /><relation>=</relation><measure rdf:datatype="xsd:float">1.0</measure></Cell></map><map><Cell><entity1 rdf:resource="&lt;http://dbkwik.webdatacommons.org/memory-alpha.wikia.com/resource/1001:_first_odyssey&gt;" /><entity2 rdf:resource="&lt;http://dbkwik.webdatacommons.org/memory-beta.wikia.com/resource/1880s&gt;" /><relation>=</relation><measure rdf:datatype="xsd:float">1.0</measure></Cell></map><map><Cell><entity1 rdf:resource="&lt;http://dbkwik.webdatacommons.org/memory-alpha.wikia.com/resource/1001:_first_odyssey&gt;" /><entity2 rdf:resource="&lt;http://dbkwik.webdatacommons.org/memory-beta.wikia.com/resource/1_centauri&gt;" /><relation>=</relation><measure rdf:datatype="xsd:float">1.0</measure></Cell></map><map><Cell><entity1 rdf:resource="&lt;http://dbkwik.webdatacommons.org/memory-alpha.wikia.com/resource/1001:_first_odyssey&gt;" /><entity2 rdf:resource="&lt;http://dbkwik.webdatacommons.org/memory-beta.wikia.com/resource/2265_starfleet_personnel_deaths&gt;" /><relation>=</relation><measure rdf:datatype="xsd:float">1.0</measure></Cell></map><map><Cell><entity1 rdf:resource="&lt;http://dbkwik.webdatacommons.org/memory-alpha.wikia.com/resource/1001:_first_odyssey&gt;" /><entity2 rdf:resource="&lt;http://dbkwik.webdatacommons.org/memory-beta.wikia.com/resource/2266_starfleet_personnel_deaths&gt;" /><relation>=</relation><measure rdf:datatype="xsd:float">1.0</measure></Cell></map><map><Cell><entity1 rdf:resource="&lt;http://dbkwik.webdatacommons.org/memory-alpha.wikia.com/resource/1001:_first_odyssey&gt;" /><entity2 rdf:resource="&lt;http://dbkwik.webdatacommons.org/memory-beta.wikia.com/resource/2267_starfleet_personnel_deaths&gt;" /><relation>=</relation><measure rdf:datatype="xsd:float">1.0</measure></Cell></map><map><Cell><entity1 rdf:resource="&lt;http://dbkwik.webdatacommons.org/memory-alpha.wikia.com/resource/1001:_first_odyssey&gt;" /><entity2 rdf:resource="&lt;http://dbkwik.webdatacommons.org/memory-beta.wikia.com/resource/2270_starfleet_personnel_deaths&gt;" /><relation>=</relation><measure rdf:datatype="xsd:float">1.0</measure></Cell></map><map><Cell><entity1 rdf:resource="&lt;http://dbkwik.webdatacommons.org/memory-alpha.wikia.com/resource/1001:_first_odyssey&gt;" /><entity2 rdf:resource="&lt;http://dbkwik.webdatacommons.org/memory-beta.wikia.com/resource/2271_starfleet_personnel_deaths&gt;" /><relation>=</relation><measure rdf:datatype="xsd:float">1.0</measure></Cell></map><map><Cell><entity1 rdf:resource="&lt;http://dbkwik.webdatacommons.org/memory-alpha.wikia.com/resource/1001:_first_odyssey&gt;" /><entity2 rdf:resource="&lt;http://dbkwik.webdatacommons.org/memory-beta.wikia.com/resource/2367_starfleet_personnel_deaths&gt;" /><relation>=</relation><measure rdf:datatype="xsd:float">1.0</measure></Cell></map><map><Cell><entity1 rdf:resource="&lt;http://dbkwik.webdatacommons.org/memory-alpha.wikia.com/resource/1001:_first_odyssey&gt;" /><entity2 rdf:resource="&lt;http://dbkwik.webdatacommons.org/memory-beta.wikia.com/resource/2373_starfleet_personnel_deaths&gt;" /><relation>=</relation><measure rdf:datatype="xsd:float">1.0</measure></Cell></map><map><Cell><entity1 rdf:resource="&lt;http://dbkwik.webdatacommons.org/memory-alpha.wikia.com/resource/10_march&gt;" /><entity2 rdf:resource="&lt;http://dbkwik.webdatacommons.org/memory-beta.wikia.com/resource/'q'uandary&gt;" /><relation>=</relation><measure rdf:datatype="xsd:float">1.0</measure></Cell></map><map><Cell><entity1 rdf:resource="&lt;http://dbkwik.webdatacommons.org/memory-alpha.wikia.com/resource/10_march&gt;" /><entity2 rdf:resource="&lt;http://dbkwik.webdatacommons.org/memory-beta.wikia.com/resource/11_lacerti&gt;" /><relation>=</relation><measure rdf:datatype="xsd:float">1.0</measure></Cell></map><map><Cell><entity1 rdf:resource="&lt;http://dbkwik.webdatacommons.org/memory-alpha.wikia.com/resource/10_march&gt;" /><entity2 rdf:resource="&lt;http://dbkwik.webdatacommons.org/memory-beta.wikia.com/resource/1616_ophiuchi_vi&gt;" /><relation>=</relation><measure rdf:datatype="xsd:float">1.0</measure></Cell></map><map><Cell><entity1 rdf:resource="&lt;http://dbkwik.webdatacommons.org/memory-alpha.wikia.com/resource/10_march&gt;" /><entity2 rdf:resource="&lt;http://dbkwik.webdatacommons.org/memory-beta.wikia.com/resource/1810s&gt;" /><relation>=</relation><measure rdf:datatype="xsd:float">1.0</measure></Cell></map><map><Cell><entity1 rdf:resource="&lt;http://dbkwik.webdatacommons.org/memory-alpha.wikia.com/resource/10_march&gt;" /><entity2 rdf:resource="&lt;http://dbkwik.webdatacommons.org/memory-beta.wikia.com/resource/1890s&gt;" /><relation>=</relation><measure rdf:datatype="xsd:float">1.0</measure></Cell></map><map><Cell><entity1 rdf:resource="&lt;http://dbkwik.webdatacommons.org/memory-alpha.wikia.com/resource/10_march&gt;" /><entity2 rdf:resource="&lt;http://dbkwik.webdatacommons.org/memory-beta.wikia.com/resource/2000-2049_sfc&gt;" /><relation>=</relation><measure rdf:datatype="xsd:float">1.0</measure></Cell></map><map><Cell><entity1 rdf:resource="&lt;http://dbkwik.webdatacommons.org/memory-alpha.wikia.com/resource/10_march&gt;" /><entity2 rdf:resource="&lt;http://dbkwik.webdatacommons.org/memory-beta.wikia.com/resource/2371_cardassian_coup&gt;" /><relation>=</relation><measure rdf:datatype="xsd:float">1.0</measure></Cell></map><map><Cell><entity1 rdf:resource="&lt;http://dbkwik.webdatacommons.org/memory-alpha.wikia.com/resource/10_march&gt;" /><entity2 rdf:resource="&lt;http://dbkwik.webdatacommons.org/memory-beta.wikia.com/resource/2371_starfleet_personnel_deaths&gt;" /><relation>=</relation><measure rdf:datatype="xsd:float">1.0</measure></Cell></map><map><Cell><entity1 rdf:resource="&lt;http://dbkwik.webdatacommons.org/memory-alpha.wikia.com/resource/10_february&gt;" /><entity2 rdf:resource="&lt;http://dbkwik.webdatacommons.org/memory-beta.wikia.com/resource/'q'uandary&gt;" /><relation>=</relation><measure rdf:datatype="xsd:float">1.0</measure></Cell></map><map><Cell><entity1 rdf:resource="&lt;http://dbkwik.webdatacommons.org/memory-alpha.wikia.com/resource/10_february&gt;" /><entity2 rdf:resource="&lt;http://dbkwik.webdatacommons.org/memory-beta.wikia.com/resource/11_lacerti&gt;" /><relation>=</relation><measure rdf:datatype="xsd:float">1.0</measure></Cell></map><map><Cell><entity1 rdf:resource="&lt;http://dbkwik.webdatacommons.org/memory-alpha.wikia.com/resource/10_february&gt;" /><entity2 rdf:resource="&lt;http://dbkwik.webdatacommons.org/memory-beta.wikia.com/resource/1616_ophiuchi_vi&gt;" /><relation>=</relation><measure rdf:datatype="xsd:float">1.0</measure></Cell></map><map><Cell><entity1 rdf:resource="&lt;http://dbkwik.webdatacommons.org/memory-alpha.wikia.com/resource/10_february&gt;" /><entity2 rdf:resource="&lt;http://dbkwik.webdatacommons.org/memory-beta.wikia.com/resource/1810s&gt;" /><relation>=</relation><measure rdf:datatype="xsd:float">1.0</measure></Cell></map><map><Cell><entity1 rdf:resource="&lt;http://dbkwik.webdatacommons.org/memory-alpha.wikia.com/resource/10_february&gt;" /><entity2 rdf:resource="&lt;http://dbkwik.webdatacommons.org/memory-beta.wikia.com/resource/1890s&gt;" /><relation>=</relation><measure rdf:datatype="xsd:float">1.0</measure></Cell></map><map><Cell><entity1 rdf:resource="&lt;http://dbkwik.webdatacommons.org/memory-alpha.wikia.com/resource/10_february&gt;" /><entity2 rdf:resource="&lt;http://dbkwik.webdatacommons.org/memory-beta.wikia.com/resource/2000-2049_sfc&gt;" /><relation>=</relation><measure rdf:datatype="xsd:float">1.0</measure></Cell></map><map><Cell><entity1 rdf:resource="&lt;http://dbkwik.webdatacommons.org/memory-alpha.wikia.com/resource/10_february&gt;" /><entity2 rdf:resource="&lt;http://dbkwik.webdatacommons.org/memory-beta.wikia.com/resource/2371_cardassian_coup&gt;" /><relation>=</relation><measure rdf:datatype="xsd:float">1.0</measure></Cell></map><map><Cell><entity1 rdf:resource="&lt;http://dbkwik.webdatacommons.org/memory-alpha.wikia.com/resource/10_february&gt;" /><entity2 rdf:resource="&lt;http://dbkwik.webdatacommons.org/memory-beta.wikia.com/resource/2371_starfleet_personnel_deaths&gt;" /><relation>=</relation><measure rdf:datatype="xsd:float">1.0</measure></Cell></map><map><Cell><entity1 rdf:resource="&lt;http://dbkwik.webdatacommons.org/memory-alpha.wikia.com/resource/10_may&gt;" /><entity2 rdf:resource="&lt;http://dbkwik.webdatacommons.org/memory-beta.wikia.com/resource/1020_octantis&gt;" /><relation>=</relation><measure rdf:datatype="xsd:float">1.0</measure></Cell></map><map><Cell><entity1 rdf:resource="&lt;http://dbkwik.webdatacommons.org/memory-alpha.wikia.com/resource/10_may&gt;" /><entity2 rdf:resource="&lt;http://dbkwik.webdatacommons.org/memory-beta.wikia.com/resource/...sacrifice_of_angels&gt;" /><relation>=</relation><measure rdf:datatype="xsd:float">1.0</measure></Cell></map><map><Cell><entity1 rdf:resource="&lt;http://dbkwik.webdatacommons.org/memory-alpha.wikia.com/resource/10_may&gt;" /><entity2 rdf:resource="&lt;http://dbkwik.webdatacommons.org/memory-beta.wikia.com/resource/127_scorpii&gt;" /><relation>=</relation><measure rdf:datatype="xsd:float">1.0</measure></Cell></map><map><Cell><entity1 rdf:resource="&lt;http://dbkwik.webdatacommons.org/memory-alpha.wikia.com/resource/10_may&gt;" /><entity2 rdf:resource="&lt;http://dbkwik.webdatacommons.org/memory-beta.wikia.com/resource/15th_squad&gt;" /><relation>=</relation><measure rdf:datatype="xsd:float">1.0</measure></Cell></map><map><Cell><entity1 rdf:resource="&lt;http://dbkwik.webdatacommons.org/memory-alpha.wikia.com/resource/10_may&gt;" /><entity2 rdf:resource="&lt;http://dbkwik.webdatacommons.org/memory-beta.wikia.com/resource/1800s&gt;" /><relation>=</relation><measure rdf:datatype="xsd:float">1.0</measure></Cell></map><map><Cell><entity1 rdf:resource="&lt;http://dbkwik.webdatacommons.org/memory-alpha.wikia.com/resource/10_may&gt;" /><entity2 rdf:resource="&lt;http://dbkwik.webdatacommons.org/memory-beta.wikia.com/resource/1810s&gt;" /><relation>=</relation><measure rdf:datatype="xsd:float">1.0</measure></Cell></map><map><Cell><entity1 rdf:resource="&lt;http://dbkwik.webdatacommons.org/memory-alpha.wikia.com/resource/10_may&gt;" /><entity2 rdf:resource="&lt;http://dbkwik.webdatacommons.org/memory-beta.wikia.com/resource/1840s&gt;" /><relation>=</relation><measure rdf:datatype="xsd:float">1.0</measure></Cell></map><map><Cell><entity1 rdf:resource="&lt;http://dbkwik.webdatacommons.org/memory-alpha.wikia.com/resource/10_may&gt;" /><entity2 rdf:resource="&lt;http://dbkwik.webdatacommons.org/memory-beta.wikia.com/resource/1865_serpens&gt;" /><relation>=</relation><measure rdf:datatype="xsd:float">1.0</measure></Cell></map><map><Cell><entity1 rdf:resource="&lt;http://dbkwik.webdatacommons.org/memory-alpha.wikia.com/resource/10_may&gt;" /><entity2 rdf:resource="&lt;http://dbkwik.webdatacommons.org/memory-beta.wikia.com/resource/1870s&gt;" /><relation>=</relation><measure rdf:datatype="xsd:float">1.0</measure></Cell></map><map><Cell><entity1 rdf:resource="&lt;http://dbkwik.webdatacommons.org/memory-alpha.wikia.com/resource/10_may&gt;" /><entity2 rdf:resource="&lt;http://dbkwik.webdatacommons.org/memory-beta.wikia.com/resource/1880s&gt;" /><relation>=</relation><measure rdf:datatype="xsd:float">1.0</measure></Cell></map><map><Cell><entity1 rdf:resource="&lt;http://dbkwik.webdatacommons.org/memory-alpha.wikia.com/resource/10_may&gt;" /><entity2 rdf:resource="&lt;http://dbkwik.webdatacommons.org/memory-beta.wikia.com/resource/1_centauri&gt;" /><relation>=</relation><measure rdf:datatype="xsd:float">1.0</measure></Cell></map><map><Cell><entity1 rdf:resource="&lt;http://dbkwik.webdatacommons.org/memory-alpha.wikia.com/resource/10_may&gt;" /><entity2 rdf:resource="&lt;http://dbkwik.webdatacommons.org/memory-beta.wikia.com/resource/2265_starfleet_personnel_deaths&gt;" /><relation>=</relation><measure rdf:datatype="xsd:float">1.0</measure></Cell></map><map><Cell><entity1 rdf:resource="&lt;http://dbkwik.webdatacommons.org/memory-alpha.wikia.com/resource/10_may&gt;" /><entity2 rdf:resource="&lt;http://dbkwik.webdatacommons.org/memory-beta.wikia.com/resource/2266_starfleet_personnel_deaths&gt;" /><relation>=</relation><measure rdf:datatype="xsd:float">1.0</measure></Cell></map><map><Cell><entity1 rdf:resource="&lt;http://dbkwik.webdatacommons.org/memory-alpha.wikia.com/resource/10_may&gt;" /><entity2 rdf:resource="&lt;http://dbkwik.webdatacommons.org/memory-beta.wikia.com/resource/2267_starfleet_personnel_deaths&gt;" /><relation>=</relation><measure rdf:datatype="xsd:float">1.0</measure></Cell></map><map><Cell><entity1 rdf:resource="&lt;http://dbkwik.webdatacommons.org/memory-alpha.wikia.com/resource/10_may&gt;" /><entity2 rdf:resource="&lt;http://dbkwik.webdatacommons.org/memory-beta.wikia.com/resource/2270_starfleet_personnel_deaths&gt;" /><relation>=</relation><measure rdf:datatype="xsd:float">1.0</measure></Cell></map><map><Cell><entity1 rdf:resource="&lt;http://dbkwik.webdatacommons.org/memory-alpha.wikia.com/resource/10_may&gt;" /><entity2 rdf:resource="&lt;http://dbkwik.webdatacommons.org/memory-beta.wikia.com/resource/2271_starfleet_personnel_deaths&gt;" /><relation>=</relation><measure rdf:datatype="xsd:float">1.0</measure></Cell></map><map><Cell><entity1 rdf:resource="&lt;http://dbkwik.webdatacommons.org/memory-alpha.wikia.com/resource/10_may&gt;" /><entity2 rdf:resource="&lt;http://dbkwik.webdatacommons.org/memory-beta.wikia.com/resource/2367_starfleet_personnel_deaths&gt;" /><relation>=</relation><measure rdf:datatype="xsd:float">1.0</measure></Cell></map><map><Cell><entity1 rdf:resource="&lt;http://dbkwik.webdatacommons.org/memory-alpha.wikia.com/resource/10_may&gt;" /><entity2 rdf:resource="&lt;http://dbkwik.webdatacommons.org/memory-beta.wikia.com/resource/2373_starfleet_personnel_deaths&gt;" /><relation>=</relation><measure rdf:datatype="xsd:float">1.0</measure></Cell></map><map><Cell><entity1 rdf:resource="&lt;http://dbkwik.webdatacommons.org/memory-alpha.wikia.com/resource/'til_death_do_us_part_(episode)&gt;" /><entity2 rdf:resource="&lt;http://dbkwik.webdatacommons.org/memory-beta.wikia.com/resource/1020_octantis&gt;" /><relation>=</relation><measure rdf:datatype="xsd:float">1.0</measure></Cell></map><map><Cell><entity1 rdf:resource="&lt;http://dbkwik.webdatacommons.org/memory-alpha.wikia.com/resource/'til_death_do_us_part_(episode)&gt;" /><entity2 rdf:resource="&lt;http://dbkwik.webdatacommons.org/memory-beta.wikia.com/resource/...sacrifice_of_angels&gt;" /><relation>=</relation><measure rdf:datatype="xsd:float">1.0</measure></Cell></map><map><Cell><entity1 rdf:resource="&lt;http://dbkwik.webdatacommons.org/memory-alpha.wikia.com/resource/'til_death_do_us_part_(episode)&gt;" /><entity2 rdf:resource="&lt;http://dbkwik.webdatacommons.org/memory-beta.wikia.com/resource/127_scorpii&gt;" /><relation>=</relation><measure rdf:datatype="xsd:float">1.0</measure></Cell></map><map><Cell><entity1 rdf:resource="&lt;http://dbkwik.webdatacommons.org/memory-alpha.wikia.com/resource/'til_death_do_us_part_(episode)&gt;" /><entity2 rdf:resource="&lt;http://dbkwik.webdatacommons.org/memory-beta.wikia.com/resource/15th_squad&gt;" /><relation>=</relation><measure rdf:datatype="xsd:float">1.0</measure></Cell></map><map><Cell><entity1 rdf:resource="&lt;http://dbkwik.webdatacommons.org/memory-alpha.wikia.com/resource/'til_death_do_us_part_(episode)&gt;" /><entity2 rdf:resource="&lt;http://dbkwik.webdatacommons.org/memory-beta.wikia.com/resource/1800s&gt;" /><relation>=</relation><measure rdf:datatype="xsd:float">1.0</measure></Cell></map><map><Cell><entity1 rdf:resource="&lt;http://dbkwik.webdatacommons.org/memory-alpha.wikia.com/resource/'til_death_do_us_part_(episode)&gt;" /><entity2 rdf:resource="&lt;http://dbkwik.webdatacommons.org/memory-beta.wikia.com/resource/1810s&gt;" /><relation>=</relation><measure rdf:datatype="xsd:float">1.0</measure></Cell></map><map><Cell><entity1 rdf:resource="&lt;http://dbkwik.webdatacommons.org/memory-alpha.wikia.com/resource/'til_death_do_us_part_(episode)&gt;" /><entity2 rdf:resource="&lt;http://dbkwik.webdatacommons.org/memory-beta.wikia.com/resource/1840s&gt;" /><relation>=</relation><measure rdf:datatype="xsd:float">1.0</measure></Cell></map><map><Cell><entity1 rdf:resource="&lt;http://dbkwik.webdatacommons.org/memory-alpha.wikia.com/resource/'til_death_do_us_part_(episode)&gt;" /><entity2 rdf:resource="&lt;http://dbkwik.webdatacommons.org/memory-beta.wikia.com/resource/1865_serpens&gt;" /><relation>=</relation><measure rdf:datatype="xsd:float">1.0</measure></Cell></map><map><Cell><entity1 rdf:resource="&lt;http://dbkwik.webdatacommons.org/memory-alpha.wikia.com/resource/'til_death_do_us_part_(episode)&gt;" /><entity2 rdf:resource="&lt;http://dbkwik.webdatacommons.org/memory-beta.wikia.com/resource/1870s&gt;" /><relation>=</relation><measure rdf:datatype="xsd:float">1.0</measure></Cell></map><map><Cell><entity1 rdf:resource="&lt;http://dbkwik.webdatacommons.org/memory-alpha.wikia.com/resource/'til_death_do_us_part_(episode)&gt;" /><entity2 rdf:resource="&lt;http://dbkwik.webdatacommons.org/memory-beta.wikia.com/resource/1880s&gt;" /><relation>=</relation><measure rdf:datatype="xsd:float">1.0</measure></Cell></map><map><Cell><entity1 rdf:resource="&lt;http://dbkwik.webdatacommons.org/memory-alpha.wikia.com/resource/'til_death_do_us_part_(episode)&gt;" /><entity2 rdf:resource="&lt;http://dbkwik.webdatacommons.org/memory-beta.wikia.com/resource/1_centauri&gt;" /><relation>=</relation><measure rdf:datatype="xsd:float">1.0</measure></Cell></map><map><Cell><entity1 rdf:resource="&lt;http://dbkwik.webdatacommons.org/memory-alpha.wikia.com/resource/'til_death_do_us_part_(episode)&gt;" /><entity2 rdf:resource="&lt;http://dbkwik.webdatacommons.org/memory-beta.wikia.com/resource/2265_starfleet_personnel_deaths&gt;" /><relation>=</relation><measure rdf:datatype="xsd:float">1.0</measure></Cell></map><map><Cell><entity1 rdf:resource="&lt;http://dbkwik.webdatacommons.org/memory-alpha.wikia.com/resource/'til_death_do_us_part_(episode)&gt;" /><entity2 rdf:resource="&lt;http://dbkwik.webdatacommons.org/memory-beta.wikia.com/resource/2266_starfleet_personnel_deaths&gt;" /><relation>=</relation><measure rdf:datatype="xsd:float">1.0</measure></Cell></map><map><Cell><entity1 rdf:resource="&lt;http://dbkwik.webdatacommons.org/memory-alpha.wikia.com/resource/'til_death_do_us_part_(episode)&gt;" /><entity2 rdf:resource="&lt;http://dbkwik.webdatacommons.org/memory-beta.wikia.com/resource/2267_starfleet_personnel_deaths&gt;" /><relation>=</relation><measure rdf:datatype="xsd:float">1.0</measure></Cell></map><map><Cell><entity1 rdf:resource="&lt;http://dbkwik.webdatacommons.org/memory-alpha.wikia.com/resource/'til_death_do_us_part_(episode)&gt;" /><entity2 rdf:resource="&lt;http://dbkwik.webdatacommons.org/memory-beta.wikia.com/resource/2270_starfleet_personnel_deaths&gt;" /><relation>=</relation><measure rdf:datatype="xsd:float">1.0</measure></Cell></map><map><Cell><entity1 rdf:resource="&lt;http://dbkwik.webdatacommons.org/memory-alpha.wikia.com/resource/'til_death_do_us_part_(episode)&gt;" /><entity2 rdf:resource="&lt;http://dbkwik.webdatacommons.org/memory-beta.wikia.com/resource/2271_starfleet_personnel_deaths&gt;" /><relation>=</relation><measure rdf:datatype="xsd:float">1.0</measure></Cell></map><map><Cell><entity1 rdf:resource="&lt;http://dbkwik.webdatacommons.org/memory-alpha.wikia.com/resource/'til_death_do_us_part_(episode)&gt;" /><entity2 rdf:resource="&lt;http://dbkwik.webdatacommons.org/memory-beta.wikia.com/resource/2367_starfleet_personnel_deaths&gt;" /><relation>=</relation><measure rdf:datatype="xsd:float">1.0</measure></Cell></map><map><Cell><entity1 rdf:resource="&lt;http://dbkwik.webdatacommons.org/memory-alpha.wikia.com/resource/'til_death_do_us_part_(episode)&gt;" /><entity2 rdf:resource="&lt;http://dbkwik.webdatacommons.org/memory-beta.wikia.com/resource/2373_starfleet_personnel_deaths&gt;" /><relation>=</relation><measure rdf:datatype="xsd:float">1.0</measure></Cell></map><map><Cell><entity1 rdf:resource="&lt;http://dbkwik.webdatacommons.org/memory-alpha.wikia.com/resource/11001001_(episode)&gt;" /><entity2 rdf:resource="&lt;http://dbkwik.webdatacommons.org/memory-beta.wikia.com/resource/1020_octantis&gt;" /><relation>=</relation><measure rdf:datatype="xsd:float">1.0</measure></Cell></map><map><Cell><entity1 rdf:resource="&lt;http://dbkwik.webdatacommons.org/memory-alpha.wikia.com/resource/11001001_(episode)&gt;" /><entity2 rdf:resource="&lt;http://dbkwik.webdatacommons.org/memory-beta.wikia.com/resource/...sacrifice_of_angels&gt;" /><relation>=</relation><measure rdf:datatype="xsd:float">1.0</measure></Cell></map><map><Cell><entity1 rdf:resource="&lt;http://dbkwik.webdatacommons.org/memory-alpha.wikia.com/resource/11001001_(episode)&gt;" /><entity2 rdf:resource="&lt;http://dbkwik.webdatacommons.org/memory-beta.wikia.com/resource/127_scorpii&gt;" /><relation>=</relation><measure rdf:datatype="xsd:float">1.0</measure></Cell></map><map><Cell><entity1 rdf:resource="&lt;http://dbkwik.webdatacommons.org/memory-alpha.wikia.com/resource/11001001_(episode)&gt;" /><entity2 rdf:resource="&lt;http://dbkwik.webdatacommons.org/memory-beta.wikia.com/resource/15th_squad&gt;" /><relation>=</relation><measure rdf:datatype="xsd:float">1.0</measure></Cell></map><map><Cell><entity1 rdf:resource="&lt;http://dbkwik.webdatacommons.org/memory-alpha.wikia.com/resource/11001001_(episode)&gt;" /><entity2 rdf:resource="&lt;http://dbkwik.webdatacommons.org/memory-beta.wikia.com/resource/1800s&gt;" /><relation>=</relation><measure rdf:datatype="xsd:float">1.0</measure></Cell></map><map><Cell><entity1 rdf:resource="&lt;http://dbkwik.webdatacommons.org/memory-alpha.wikia.com/resource/11001001_(episode)&gt;" /><entity2 rdf:resource="&lt;http://dbkwik.webdatacommons.org/memory-beta.wikia.com/resource/1810s&gt;" /><relation>=</relation><measure rdf:datatype="xsd:float">1.0</measure></Cell></map><map><Cell><entity1 rdf:resource="&lt;http://dbkwik.webdatacommons.org/memory-alpha.wikia.com/resource/11001001_(episode)&gt;" /><entity2 rdf:resource="&lt;http://dbkwik.webdatacommons.org/memory-beta.wikia.com/resource/1840s&gt;" /><relation>=</relation><measure rdf:datatype="xsd:float">1.0</measure></Cell></map><map><Cell><entity1 rdf:resource="&lt;http://dbkwik.webdatacommons.org/memory-alpha.wikia.com/resource/11001001_(episode)&gt;" /><entity2 rdf:resource="&lt;http://dbkwik.webdatacommons.org/memory-beta.wikia.com/resource/1865_serpens&gt;" /><relation>=</relation><measure rdf:datatype="xsd:float">1.0</measure></Cell></map><map><Cell><entity1 rdf:resource="&lt;http://dbkwik.webdatacommons.org/memory-alpha.wikia.com/resource/11001001_(episode)&gt;" /><entity2 rdf:resource="&lt;http://dbkwik.webdatacommons.org/memory-beta.wikia.com/resource/1870s&gt;" /><relation>=</relation><measure rdf:datatype="xsd:float">1.0</measure></Cell></map><map><Cell><entity1 rdf:resource="&lt;http://dbkwik.webdatacommons.org/memory-alpha.wikia.com/resource/11001001_(episode)&gt;" /><entity2 rdf:resource="&lt;http://dbkwik.webdatacommons.org/memory-beta.wikia.com/resource/1880s&gt;" /><relation>=</relation><measure rdf:datatype="xsd:float">1.0</measure></Cell></map><map><Cell><entity1 rdf:resource="&lt;http://dbkwik.webdatacommons.org/memory-alpha.wikia.com/resource/11001001_(episode)&gt;" /><entity2 rdf:resource="&lt;http://dbkwik.webdatacommons.org/memory-beta.wikia.com/resource/1_centauri&gt;" /><relation>=</relation><measure rdf:datatype="xsd:float">1.0</measure></Cell></map><map><Cell><entity1 rdf:resource="&lt;http://dbkwik.webdatacommons.org/memory-alpha.wikia.com/resource/11001001_(episode)&gt;" /><entity2 rdf:resource="&lt;http://dbkwik.webdatacommons.org/memory-beta.wikia.com/resource/2265_starfleet_personnel_deaths&gt;" /><relation>=</relation><measure rdf:datatype="xsd:float">1.0</measure></Cell></map><map><Cell><entity1 rdf:resource="&lt;http://dbkwik.webdatacommons.org/memory-alpha.wikia.com/resource/11001001_(episode)&gt;" /><entity2 rdf:resource="&lt;http://dbkwik.webdatacommons.org/memory-beta.wikia.com/resource/2266_starfleet_personnel_deaths&gt;" /><relation>=</relation><measure rdf:datatype="xsd:float">1.0</measure></Cell></map><map><Cell><entity1 rdf:resource="&lt;http://dbkwik.webdatacommons.org/memory-alpha.wikia.com/resource/11001001_(episode)&gt;" /><entity2 rdf:resource="&lt;http://dbkwik.webdatacommons.org/memory-beta.wikia.com/resource/2267_starfleet_personnel_deaths&gt;" /><relation>=</relation><measure rdf:datatype="xsd:float">1.0</measure></Cell></map><map><Cell><entity1 rdf:resource="&lt;http://dbkwik.webdatacommons.org/memory-alpha.wikia.com/resource/11001001_(episode)&gt;" /><entity2 rdf:resource="&lt;http://dbkwik.webdatacommons.org/memory-beta.wikia.com/resource/2270_starfleet_personnel_deaths&gt;" /><relation>=</relation><measure rdf:datatype="xsd:float">1.0</measure></Cell></map><map><Cell><entity1 rdf:resource="&lt;http://dbkwik.webdatacommons.org/memory-alpha.wikia.com/resource/11001001_(episode)&gt;" /><entity2 rdf:resource="&lt;http://dbkwik.webdatacommons.org/memory-beta.wikia.com/resource/2271_starfleet_personnel_deaths&gt;" /><relation>=</relation><measure rdf:datatype="xsd:float">1.0</measure></Cell></map><map><Cell><entity1 rdf:resource="&lt;http://dbkwik.webdatacommons.org/memory-alpha.wikia.com/resource/11001001_(episode)&gt;" /><entity2 rdf:resource="&lt;http://dbkwik.webdatacommons.org/memory-beta.wikia.com/resource/2367_starfleet_personnel_deaths&gt;" /><relation>=</relation><measure rdf:datatype="xsd:float">1.0</measure></Cell></map><map><Cell><entity1 rdf:resource="&lt;http://dbkwik.webdatacommons.org/memory-alpha.wikia.com/resource/11001001_(episode)&gt;" /><entity2 rdf:resource="&lt;http://dbkwik.webdatacommons.org/memory-beta.wikia.com/resource/2373_starfleet_personnel_deaths&gt;" /><relation>=</relation><measure rdf:datatype="xsd:float">1.0</measure></Cell></map><map><Cell><entity1 rdf:resource="&lt;http://dbkwik.webdatacommons.org/memory-alpha.wikia.com/resource/10_september&gt;" /><entity2 rdf:resource="&lt;http://dbkwik.webdatacommons.org/memory-beta.wikia.com/resource/1020_octantis&gt;" /><relation>=</relation><measure rdf:datatype="xsd:float">1.0</measure></Cell></map><map><Cell><entity1 rdf:resource="&lt;http://dbkwik.webdatacommons.org/memory-alpha.wikia.com/resource/10_september&gt;" /><entity2 rdf:resource="&lt;http://dbkwik.webdatacommons.org/memory-beta.wikia.com/resource/...sacrifice_of_angels&gt;" /><relation>=</relation><measure rdf:datatype="xsd:float">1.0</measure></Cell></map><map><Cell><entity1 rdf:resource="&lt;http://dbkwik.webdatacommons.org/memory-alpha.wikia.com/resource/10_september&gt;" /><entity2 rdf:resource="&lt;http://dbkwik.webdatacommons.org/memory-beta.wikia.com/resource/127_scorpii&gt;" /><relation>=</relation><measure rdf:datatype="xsd:float">1.0</measure></Cell></map><map><Cell><entity1 rdf:resource="&lt;http://dbkwik.webdatacommons.org/memory-alpha.wikia.com/resource/10_september&gt;" /><entity2 rdf:resource="&lt;http://dbkwik.webdatacommons.org/memory-beta.wikia.com/resource/15th_squad&gt;" /><relation>=</relation><measure rdf:datatype="xsd:float">1.0</measure></Cell></map><map><Cell><entity1 rdf:resource="&lt;http://dbkwik.webdatacommons.org/memory-alpha.wikia.com/resource/10_september&gt;" /><entity2 rdf:resource="&lt;http://dbkwik.webdatacommons.org/memory-beta.wikia.com/resource/1800s&gt;" /><relation>=</relation><measure rdf:datatype="xsd:float">1.0</measure></Cell></map><map><Cell><entity1 rdf:resource="&lt;http://dbkwik.webdatacommons.org/memory-alpha.wikia.com/resource/10_september&gt;" /><entity2 rdf:resource="&lt;http://dbkwik.webdatacommons.org/memory-beta.wikia.com/resource/1810s&gt;" /><relation>=</relation><measure rdf:datatype="xsd:float">1.0</measure></Cell></map><map><Cell><entity1 rdf:resource="&lt;http://dbkwik.webdatacommons.org/memory-alpha.wikia.com/resource/10_september&gt;" /><entity2 rdf:resource="&lt;http://dbkwik.webdatacommons.org/memory-beta.wikia.com/resource/1840s&gt;" /><relation>=</relation><measure rdf:datatype="xsd:float">1.0</measure></Cell></map><map><Cell><entity1 rdf:resource="&lt;http://dbkwik.webdatacommons.org/memory-alpha.wikia.com/resource/10_september&gt;" /><entity2 rdf:resource="&lt;http://dbkwik.webdatacommons.org/memory-beta.wikia.com/resource/1865_serpens&gt;" /><relation>=</relation><measure rdf:datatype="xsd:float">1.0</measure></Cell></map><map><Cell><entity1 rdf:resource="&lt;http://dbkwik.webdatacommons.org/memory-alpha.wikia.com/resource/10_september&gt;" /><entity2 rdf:resource="&lt;http://dbkwik.webdatacommons.org/memory-beta.wikia.com/resource/1870s&gt;" /><relation>=</relation><measure rdf:datatype="xsd:float">1.0</measure></Cell></map><map><Cell><entity1 rdf:resource="&lt;http://dbkwik.webdatacommons.org/memory-alpha.wikia.com/resource/10_september&gt;" /><entity2 rdf:resource="&lt;http://dbkwik.webdatacommons.org/memory-beta.wikia.com/resource/1880s&gt;" /><relation>=</relation><measure rdf:datatype="xsd:float">1.0</measure></Cell></map><map><Cell><entity1 rdf:resource="&lt;http://dbkwik.webdatacommons.org/memory-alpha.wikia.com/resource/10_september&gt;" /><entity2 rdf:resource="&lt;http://dbkwik.webdatacommons.org/memory-beta.wikia.com/resource/1_centauri&gt;" /><relation>=</relation><measure rdf:datatype="xsd:float">1.0</measure></Cell></map><map><Cell><entity1 rdf:resource="&lt;http://dbkwik.webdatacommons.org/memory-alpha.wikia.com/resource/10_september&gt;" /><entity2 rdf:resource="&lt;http://dbkwik.webdatacommons.org/memory-beta.wikia.com/resource/2265_starfleet_personnel_deaths&gt;" /><relation>=</relation><measure rdf:datatype="xsd:float">1.0</measure></Cell></map></Alignment></rdf:RDF>